<?xml version="1.0" encoding="utf-8"?><toc><breadcrumbs><li><a href="98399376-cf41-9454-4b4d-4fab2ca20bc7.htm">Docs</a></li><li><a href="79d2eac2-21f4-54ff-7552-b20c33c30600.htm">Krypton.<wbr />Toolkit</a></li><li><a href="99324d69-1df2-d667-2822-25e081918839.htm">String<wbr />Lookup<wbr />Converter&lt;TEnum<wbr />Type&gt;</a></li></breadcrumbs><tocItems><li><a id="d3cfd912-6c2a-8865-d8af-0b4a79da30da" href="d3cfd912-6c2a-8865-d8af-0b4a79da30da.htm">Constructor</a></li><li><a id="2a2e1dcf-96c8-3773-e02b-2f9b67581262" class="has-submenu" href="2a2e1dcf-96c8-3773-e02b-2f9b67581262.htm"><span data-tocFile="../toc/IDB0140D.xml" class="icon toggle" onclick="ToggleExpandCollapse(this); return false;"><i class="fa fa-angle-right"> </i></span>Properties</a><ul class="toc-menu is-hidden"> </ul></li><li><a id="d22a4c9b-ef6c-4ce5-b344-28e40d08bad5" class="has-submenu" href="d22a4c9b-ef6c-4ce5-b344-28e40d08bad5.htm"><span data-tocFile="../toc/IDC0140D.xml" class="icon toggle" onclick="ToggleExpandCollapse(this); return false;"><i class="fa fa-angle-right"> </i></span>Methods</a><ul class="toc-menu is-hidden"> </ul></li></tocItems></toc>