<?xml version="1.0" encoding="utf-8"?><toc><breadcrumbs><li><a href="98399376-cf41-9454-4b4d-4fab2ca20bc7.htm">Docs</a></li><li><a href="79d2eac2-21f4-54ff-7552-b20c33c30600.htm">Krypton.<wbr />Toolkit</a></li><li><a href="2ada1742-b501-4f19-8766-507ddaee90ff.htm">Krypton<wbr />Context<wbr />Menu<wbr />Check<wbr />Box</a></li></breadcrumbs><tocItems><li><a id="7b1e3248-cf85-d052-d538-6e76f0b2da8e" class="has-submenu" href="7b1e3248-cf85-d052-d538-6e76f0b2da8e.htm"><span data-tocFile="../toc/IDA0BI0D.xml" class="icon toggle" onclick="ToggleExpandCollapse(this); return false;"><i class="fa fa-angle-right"> </i></span>Constructors</a><ul class="toc-menu is-hidden"> </ul></li><li><a id="9a30269d-cbae-fd3a-e5d2-548d054a793f" class="has-submenu" href="9a30269d-cbae-fd3a-e5d2-548d054a793f.htm"><span data-tocFile="../toc/IDB0BI0D.xml" class="icon toggle" onclick="ToggleExpandCollapse(this); return false;"><i class="fa fa-angle-right"> </i></span>Properties</a><ul class="toc-menu is-hidden"> </ul></li><li><a id="48715ce4-769f-ecfc-1a92-a672aa29a9b1" class="has-submenu" href="48715ce4-769f-ecfc-1a92-a672aa29a9b1.htm"><span data-tocFile="../toc/IDC0BI0D.xml" class="icon toggle" onclick="ToggleExpandCollapse(this); return false;"><i class="fa fa-angle-right"> </i></span>Methods</a><ul class="toc-menu is-hidden"> </ul></li><li><a id="cf66081f-2528-f214-eadb-388fde00c275" class="has-submenu" href="cf66081f-2528-f214-eadb-388fde00c275.htm"><span data-tocFile="../toc/IDD0BI0D.xml" class="icon toggle" onclick="ToggleExpandCollapse(this); return false;"><i class="fa fa-angle-right"> </i></span>Events</a><ul class="toc-menu is-hidden"> </ul></li></tocItems></toc>