<?xml version="1.0" encoding="utf-8"?><toc><breadcrumbs><li><a href="98399376-cf41-9454-4b4d-4fab2ca20bc7.htm">Docs</a></li><li><a href="79d2eac2-21f4-54ff-7552-b20c33c30600.htm">Krypton.<wbr />Toolkit</a></li><li><a href="3818a9d7-2336-9c74-c640-ee76137bda16.htm">Memento<wbr />Ribbon<wbr />Linear</a></li></breadcrumbs><tocItems><li><a id="87716f0f-585c-5eb6-e745-14a6a6065157" href="87716f0f-585c-5eb6-e745-14a6a6065157.htm">Constructor</a></li><li><a id="d20f0709-a994-c2f1-665f-54ef2521d3fc" class="has-submenu" href="d20f0709-a994-c2f1-665f-54ef2521d3fc.htm"><span data-tocFile="../toc/IDB0BS0D.xml" class="icon toggle" onclick="ToggleExpandCollapse(this); return false;"><i class="fa fa-angle-right"> </i></span>Methods</a><ul class="toc-menu is-hidden"> </ul></li><li><a id="0559d080-2940-1295-f5f6-4c73364a8a06" class="has-submenu" href="0559d080-2940-1295-f5f6-4c73364a8a06.htm"><span data-tocFile="../toc/IDC0BS0D.xml" class="icon toggle" onclick="ToggleExpandCollapse(this); return false;"><i class="fa fa-angle-right"> </i></span>Fields</a><ul class="toc-menu is-hidden"> </ul></li></tocItems></toc>