<?xml version="1.0" encoding="utf-8"?><toc><breadcrumbs><li><a href="98399376-cf41-9454-4b4d-4fab2ca20bc7.htm">Docs</a></li><li><a href="79d2eac2-21f4-54ff-7552-b20c33c30600.htm">Krypton.<wbr />Toolkit</a></li><li><a href="52b19374-1f8b-781f-0f56-500e31c51106.htm">Context<wbr />Menu<wbr />Args</a></li></breadcrumbs><tocItems><li><a id="fc9671ec-4dca-c9d3-5813-634ff56af7e4" class="has-submenu" href="fc9671ec-4dca-c9d3-5813-634ff56af7e4.htm"><span data-tocFile="../toc/IDA0FC0D.xml" class="icon toggle" onclick="ToggleExpandCollapse(this); return false;"><i class="fa fa-angle-right"> </i></span>Constructors</a><ul class="toc-menu is-hidden"> </ul></li><li><a id="3ebffe2f-cd2e-cf11-a055-d28faeacc21e" class="has-submenu" href="3ebffe2f-cd2e-cf11-a055-d28faeacc21e.htm"><span data-tocFile="../toc/IDB0FC0D.xml" class="icon toggle" onclick="ToggleExpandCollapse(this); return false;"><i class="fa fa-angle-right"> </i></span>Properties</a><ul class="toc-menu is-hidden"> </ul></li><li><a id="78583013-1e38-81f8-f3a6-b613e8e43736" href="78583013-1e38-81f8-f3a6-b613e8e43736.htm">Methods</a></li></tocItems></toc>