<?xml version="1.0" encoding="utf-8"?><toc><breadcrumbs><li><a href="98399376-cf41-9454-4b4d-4fab2ca20bc7.htm">Docs</a></li><li><a href="79d2eac2-21f4-54ff-7552-b20c33c30600.htm">Krypton.<wbr />Toolkit</a></li><li><a href="e2ab5372-e9f0-ed9b-e503-75ccfc6fd40c.htm">Context<wbr />Menu<wbr />Images</a></li></breadcrumbs><tocItems><li><a id="ac80221b-fcb8-544e-d908-390877d7b2ac" href="ac80221b-fcb8-544e-d908-390877d7b2ac.htm">Constructor</a></li><li><a id="b0a51b29-11de-416a-eaea-8775eb739f41" class="has-submenu" href="b0a51b29-11de-416a-eaea-8775eb739f41.htm"><span data-tocFile="../toc/IDB0HC0D.xml" class="icon toggle" onclick="ToggleExpandCollapse(this); return false;"><i class="fa fa-angle-right"> </i></span>Properties</a><ul class="toc-menu is-hidden"> </ul></li><li><a id="ebab916f-0477-fc63-a644-5dc278d805aa" class="has-submenu" href="ebab916f-0477-fc63-a644-5dc278d805aa.htm"><span data-tocFile="../toc/IDC0HC0D.xml" class="icon toggle" onclick="ToggleExpandCollapse(this); return false;"><i class="fa fa-angle-right"> </i></span>Methods</a><ul class="toc-menu is-hidden"> </ul></li></tocItems></toc>