<?xml version="1.0" encoding="utf-8"?><toc><breadcrumbs><li><a href="98399376-cf41-9454-4b4d-4fab2ca20bc7.htm">Docs</a></li><li><a href="79d2eac2-21f4-54ff-7552-b20c33c30600.htm">Krypton.<wbr />Toolkit</a></li><li><a href="d2cabb84-98fc-d1e9-e5d6-a53e786e29fe.htm">Krypton<wbr />Palette<wbr />Tab<wbr />Button</a></li></breadcrumbs><tocItems><li><a id="75c9b793-3460-0475-13cc-43696baf4a42" href="75c9b793-3460-0475-13cc-43696baf4a42.htm">Constructor</a></li><li><a id="cca9929e-80b8-9b7c-871d-23e27bda9de0" class="has-submenu" href="cca9929e-80b8-9b7c-871d-23e27bda9de0.htm"><span data-tocFile="../toc/IDB0LO0D.xml" class="icon toggle" onclick="ToggleExpandCollapse(this); return false;"><i class="fa fa-angle-right"> </i></span>Properties</a><ul class="toc-menu is-hidden"> </ul></li><li><a id="c34a3318-6ad1-10a6-cdaa-3ebddaf70e35" class="has-submenu" href="c34a3318-6ad1-10a6-cdaa-3ebddaf70e35.htm"><span data-tocFile="../toc/IDC0LO0D.xml" class="icon toggle" onclick="ToggleExpandCollapse(this); return false;"><i class="fa fa-angle-right"> </i></span>Methods</a><ul class="toc-menu is-hidden"> </ul></li></tocItems></toc>