<?xml version="1.0" encoding="utf-8"?><toc><breadcrumbs><li><a href="98399376-cf41-9454-4b4d-4fab2ca20bc7.htm">Docs</a></li><li><a href="79d2eac2-21f4-54ff-7552-b20c33c30600.htm">Krypton.<wbr />Toolkit</a></li><li><a href="e5103b02-6fb2-257f-7b4d-f5f4670489a2.htm">Memento<wbr />Ribbon<wbr />Linear<wbr />Border</a></li><li><a href="7f02f711-f2a5-4801-1cd5-9f1dfc6a0cef.htm">Methods</a></li></breadcrumbs><tocItems><li><a id="dabcf59b-f02e-fe9f-a752-a73afd34fab0" class="has-submenu" href="dabcf59b-f02e-fe9f-a752-a73afd34fab0.htm"><span data-tocFile="../toc/IDAB0CS0D.xml" class="icon toggle" onclick="ToggleExpandCollapse(this); return false;"><i class="fa fa-angle-right"> </i></span>Dispose</a><ul class="toc-menu is-hidden"> </ul></li></tocItems></toc>